{
  "placeholderImages": [
    {
      "id": "hero-mountains",
      "description": "Lush green mountains of Arunachal Pradesh",
      "imageUrl": "https://images.unsplash.com/photo-1464822759023-fed622ff2c3b?w=1080&h=720&fit=crop&auto=format&q=80",
      "imageHint": "green mountains"
    },
    {
      "id": "hero-himalaya",
      "description": "Snow-capped Himalayan peaks at dawn",
      "imageUrl": "https://images.unsplash.com/photo-1506905925346-21bda4d32df4?w=1080&h=720&fit=crop&auto=format&q=80",
      "imageHint": "himalaya snow peaks"
    },
    {
      "id": "hero-valley",
      "description": "Scenic valley with river and forest in North-East India",
      "imageUrl": "https://images.unsplash.com/photo-1501854140801-50d01698950b?w=1080&h=720&fit=crop&auto=format&q=80",
      "imageHint": "green valley river"
    },
    {
      "id": "hero-monastery",
      "description": "Ancient monastery perched on a hilltop",
      "imageUrl": "https://images.unsplash.com/photo-1548013146-72479768bada?w=1080&h=720&fit=crop&auto=format&q=80",
      "imageHint": "monastery hilltop"
    },
    {
      "id": "dest-tawang",
      "description": "Tawang town and monastery panorama",
      "imageUrl": "https://images.unsplash.com/photo-1545243424-0ce743bbb3e5?w=1080&h=720&fit=crop&auto=format&q=80",
      "imageHint": "tawang monastery"
    },
    {
      "id": "dest-ziro",
      "description": "Ziro Valley rice fields and Apatani villages",
      "imageUrl": "https://images.unsplash.com/photo-1501854140801-50d01698950b?w=1080&h=720&fit=crop&auto=format&q=80",
      "imageHint": "rice terraces valley"
    },
    {
      "id": "dest-namdapha",
      "description": "Dense jungle of Namdapha National Park",
      "imageUrl": "https://images.unsplash.com/photo-1448375240586-882707db888b?w=1080&h=720&fit=crop&auto=format&q=80",
      "imageHint": "dense jungle forest"
    },
    {
      "id": "dest-mechuka",
      "description": "Mechuka valley surrounded by snowy mountains",
      "imageUrl": "https://images.unsplash.com/photo-1519681393784-d120267933ba?w=1080&h=720&fit=crop&auto=format&q=80",
      "imageHint": "snowy mountain valley"
    },
    {
      "id": "dest-sangti",
      "description": "Sangti Valley with black-necked cranes",
      "imageUrl": "https://images.unsplash.com/photo-1505118380757-91f5f5632de0?w=1080&h=720&fit=crop&auto=format&q=80",
      "imageHint": "serene mountain river"
    },
    {
      "id": "hotel-tawang",
      "description": "Cozy mountain resort in Tawang",
      "imageUrl": "https://images.unsplash.com/photo-1542314831-068cd1dbfeeb?w=1080&h=720&fit=crop&auto=format&q=80",
      "imageHint": "mountain resort"
    },
    {
      "id": "hotel-ziro",
      "description": "Eco-stay in Ziro valley",
      "imageUrl": "https://images.unsplash.com/photo-1520250497591-112f2f40a3f4?w=1080&h=720&fit=crop&auto=format&q=80",
      "imageHint": "valley stay"
    },
    {
      "id": "transport-suv",
      "description": "SUV for mountain travel",
      "imageUrl": "https://images.unsplash.com/photo-1464822759023-fed622ff2c3b?w=1080&h=720&fit=crop&auto=format&q=80",
      "imageHint": "mountain suv"
    },
    {
      "id": "transport-bike",
      "description": "Royal Enfield for Himalayan tours",
      "imageUrl": "https://images.unsplash.com/photo-1506905925346-21bda4d32df4?w=1080&h=720&fit=crop&auto=format&q=80",
      "imageHint": "adventure bike"
    },
    {
      "id": "culture-monastery",
      "description": "Tawang Monastery landscape",
      "imageUrl": "https://images.unsplash.com/photo-1545243424-0ce743bbb3e5?w=1080&h=720&fit=crop&auto=format&q=80",
      "imageHint": "buddhist monastery"
    },
    {
      "id": "hospital-safety",
      "description": "Modern hospital facility",
      "imageUrl": "https://images.unsplash.com/photo-1519494026892-80bbd2d6fd0d?w=1080&h=720&fit=crop&auto=format&q=80",
      "imageHint": "hospital building"
    }
  ]
}